sample_id/__init__.py
sample_id/analysis.py
sample_id/ann/__init__.py
sample_id/ann/ann.py
sample_id/ann/annoy.py
sample_id/ann/hive.py
sample_id/ann/hough.py
sample_id/ann/query.py
sample_id/audio.py
sample_id/cli.py
sample_id/deprecated/deprecated_ann.py
sample_id/deprecated/deprecated_hough.py
sample_id/deprecated/deprecated_main.py
sample_id/fingerprint/__init__.py
sample_id/fingerprint/fingerprint.py
sample_id/fingerprint/sift/__init__.py
sample_id/fingerprint/sift/opencv.py
sample_id/fingerprint/sift/sift.py
sample_id/fingerprint/sift/vlfeat.py
sample_id/fingerprint/spectral_peaks.py
sample_id/io.py
sample_id/main.py
sample_id/trackio.py
sample_id/util.py
sample_id-0.1.27.dist-info/entry_points.txt
sample_id-0.1.27.dist-info/LICENSE
sample_id-0.1.27.dist-info/WHEEL
sample_id-0.1.27.dist-info/METADATA
sample_id-0.1.27.dist-info/RECORD
